Workbook

Sheet INSTRUCTIONS
B2: 13-WEEK ROLLING CASH FLOW FORECAST MODEL
B3: Naicents Ltd | Kenya Financial Consultancy | Client-Facing Advisory Tool
B5: PURPOSE
B6: This model provides a formula-driven 13-week rolling cash flow forecast for Kenyan SME clients. It enables Base, Stress, and Upside scenario analysis to support cash planning, working capital management, and conversations with management, boards, and lenders. No macros or VBA are used.
B8: WORKBOOK STRUCTURE
B9: INSTRUCTIONS | C9: This tab. Read before use.
B10: ASSUMPTIONS | C10: All editable inputs. Blue shaded cells only. Do not edit black formula cells.
B11: CASHFLOW | C11: 13-week rolling model. Loan Drawdowns row accepts manual weekly input.
B12: DASHBOARD | C12: Visual summary: KPI metrics, weekly balance chart, scenario comparison.
B14: HOW TO USE
B15: Step 1 | C15: ASSUMPTIONS tab, cell B6: Enter the Monday that begins the 13-week forecast period.
B16: Step 2 | C16: ASSUMPTIONS tab, cell B7: Select Active Scenario from the dropdown (Base / Stress / Upside).
B17: Step 3 | C17: ASSUMPTIONS tab, cell B8: Set the Minimum Cash Threshold (client cash buffer floor).
B18: Step 4 | C18: ASSUMPTIONS tab, cell B9: Enter the opening cash and bank balance at the start of Week 1.
B19: Step 5 | C19: ASSUMPTIONS tab, column B: Update Weekly Base Amounts for each category to match client actuals.
B20: Step 6 | C20: ASSUMPTIONS tab, columns D-F: Adjust scenario multipliers to reflect your advisory view.
B21: Step 7 | C21: CASHFLOW tab, row 10: Enter one-off Loan Drawdown amounts in relevant week columns (blue cells).
B22: Step 8 | C22: Review the DASHBOARD for the balance chart, minimum cash warning, and scenario comparison.
B24: KRA REMITTANCE SCHEDULE
B25: PAYE | C25: Due by 9th of the following month. File P10 and remit via KRA iTax portal.
B26: VAT | C26: Due by 20th of the following month. File VAT3 return via iTax.
B27: NSSF | C27: Due by last day of each month. KES 200 employee + KES 200 employer per employee.
B28: NHIF / SHIF | C28: Due by last day of each month. Rates graduated under the SHIF framework.
B29: Corp. Income Tax | C29: Quarterly instalment payments (1st-4th). Annual return within 6 months of year-end.
B30: Withholding Tax | C30: Due by 20th of following month (professional fees, rent, dividends, etc.).
B32: COLOR CODING GUIDE
B33: Blue text on shaded cell | C33: Editable input. You may change this value.
B34: Black text on white cell | C34: Calculated formula. Do not edit.
B35: Green text on white cell | C35: Cross-sheet formula link. Do not edit.
B37: DISCLAIMER
B38: This model is prepared by Naicents Ltd for financial planning and advisory purposes only. It is based on client-agreed assumptions and does not constitute audited financial statements or a guarantee of future cash flows. Naicents Ltd accepts no liability for business decisions made on the basis of this forecast.

Sheet ASSUMPTIONS
A2: ASSUMPTIONS & SCENARIO SETTINGS
A3: Naicents Ltd | Blue cells are editable inputs | Do not edit formula cells (black text)
A5: MODEL CONFIGURATION
A6: Start Date (Monday of Week 1) | B6: 45782 | C6: Enter the Monday that begins the forecast period.
A7: Active Scenario | B7: Base | C7: Select from dropdown: Base | Stress | Upside
A8: Minimum Cash Threshold (KES) | B8: 500000 | C8: Dashboard warning triggers if any week closes below this amount.
A9: Opening Cash Balance (KES) | B9: 850000 | C9: Total cash + bank balance at the very start of Week 1.
A11: INFLOW ASSUMPTIONS
A12: Category | B12: Weekly Base (KES) | C12: Notes / Timing | D12: Base | E12: Stress | F12: Upside
A13: Sales Collections | B13: 900000 | C13: Trade receivables + cash sales | D13: 1 | E13: 0.7 | F13: 1.2
A14: Loan Drawdowns | B14: 0 | C14: Enter directly in Cash Flow tab | D14: 1 | E14: 1 | F14: 1
A15: Other Income | B15: 50000 | C15: VAT refunds, rebates, interest received | D15: 1 | E15: 0.8 | F15: 1.1
A17: OUTFLOW ASSUMPTIONS
A18: Category | B18: Weekly Base (KES) | C18: Notes / Timing | D18: Base | E18: Stress | F18: Upside
A19: Suppliers / Stock Purchases | B19: 420000 | C19: Payments to trade creditors | D19: 1 | E19: 1.1 | F19: 0.9
A20: Salaries & Wages | B20: 62500 | C20: KES 250K/month spread over 4 weeks | D20: 1 | E20: 1 | F20: 1
A21: PAYE Remittance | B21: 11250 | C21: Avg KES 45K/month. KRA due 9th of following month | D21: 1 | E21: 1 | F21: 1
A22: VAT Remittance | B22: 22500 | C22: Avg KES 90K/month. KRA due 20th of following month | D22: 1 | E22: 1 | F22: 1
A23: NSSF Contributions | B23: 3000 | C23: Employee & employer share. Due month-end | D23: 1 | E23: 1 | F23: 1
A24: NHIF / SHIF Contributions | B24: 3750 | C24: Social health insurance. Due month-end | D24: 1 | E24: 1 | F24: 1
A25: Rent | B25: 21250 | C25: Avg KES 85K/month. Paid at start of month | D25: 1 | E25: 1 | F25: 1
A26: Utilities | B26: 25000 | C26: Electricity, water, internet | D26: 1 | E26: 1.2 | F26: 0.9
A27: Loan Repayments | B27: 15000 | C27: Avg KES 60K/month. Bank instalment | D27: 1 | E27: 1 | F27: 1
A28: Other Overheads | B28: 35000 | C28: Admin, transport, sundry expenses | D28: 1 | E28: 1.1 | F28: 0.9
A30: SCENARIO GUIDE
A31: Base | B31: Normal operating conditions. All multipliers = 1.00x.
A32: Stress | B32: Revenue decline (sales -30%, other income -20%) + cost pressures (suppliers +10%, utilities +20%, overheads +10%). Models slow collections or supply disruption.
A33: Upside | B33: Strong trading (sales +20%, other income +10%) + efficiencies (suppliers -10%, utilities -10%, overheads -10%). Models a peak sales quarter.

Sheet CASHFLOW
A2: 13-WEEK ROLLING CASH FLOW FORECAST
A3: =ASSUMPTIONS!$B$7&" Scenario | Period: "&TEXT(ASSUMPTIONS!$B$6,"DD-MMM-YY")&" to "&TEXT(ASSUMPTIONS!$B$6+90,"DD-MMM-YY") -> Base Scenario | Period: 05-May-25 to 03-Aug-25
A5: Description | B5: Notes | C5: Wk 1 | D5: Wk 2 | E5: Wk 3 | F5: Wk 4 | G5: Wk 5 | H5: Wk 6 | I5: Wk 7 | J5: Wk 8 | K5: Wk 9 | L5: Wk 10 | M5: Wk 11 | N5: Wk 12 | O5: Wk 13 | P5: 13-WK TOTAL
A6: Week Commencing | C6: =ASSUMPTIONS!$B$6 -> 45782 | D6: =C6+7 -> 45789 | E6: =D6+7 -> 45796 | F6: =E6+7 -> 45803 | G6: =F6+7 -> 45810 | H6: =G6+7 -> 45817 | I6: =H6+7 -> 45824 | J6: =I6+7 -> 45831 | K6: =J6+7 -> 45838 | ... O6: =N6+7 -> 45866
A7: OPENING BALANCE | B7: Cash & bank balance at start of each week | C7: =ASSUMPTIONS!$B$9 -> 850000 | D7: =C26 -> 1180750 | E7: =D26 -> 1511500 | F7: =E26 -> 1842250 | G7: =F26 -> 2173000 | H7: =G26 -> 2503750 | I7: =H26 -> 2834500 | J7: =I26 -> 3165250 | K7: =J26 -> 3496000 | ... O7: =N26 -> 4819000 | P7: =C7 -> 850000
A8: INFLOWS
A9: Sales Collections | B9: Trade receivables + cash sales | C9: =ASSUMPTIONS!$B$13*CHOOSE(MATCH(ASSUMPTIONS!$B$7,{"Base","Stress","Upside"},0),ASSUMPTIONS!$D$13,ASSUMPTIONS!$E$13,ASSUMPTIONS!$F$13) -> 900000 | D9: =ASSUMPTIONS!$B$13*CHOOSE(MATCH(ASSUMPTIONS!$B$7,{"Base","Stress","Upside"},0),ASSUMPTIONS!$D$13,ASSUMPTIONS!$E$13,ASSUMPTIONS!$F$13) -> 900000 | E9: =ASSUMPTIONS!$B$13*CHOOSE(MATCH(ASSUMPTIONS!$B$7,{"Base","Stress","Upside"},0),ASSUMPTIONS!$D$13,ASSUMPTIONS!$E$13,ASSUMPTIONS!$F$13) -> 900000 | F9: =ASSUMPTIONS!$B$13*CHOOSE(MATCH(ASSUMPTIONS!$B$7,{"Base","Stress","Upside"},0),ASSUMPTIONS!$D$13,ASSUMPTIONS!$E$13,ASSUMPTIONS!$F$13) -> 900000 | G9: =ASSUMPTIONS!$B$13*CHOOSE(MATCH(ASSUMPTIONS!$B$7,{"Base","Stress","Upside"},0),ASSUMPTIONS!$D$13,ASSUMPTIONS!$E$13,ASSUMPTIONS!$F$13) -> 900000 | H9: =ASSUMPTIONS!$B$13*CHOOSE(MATCH(ASSUMPTIONS!$B$7,{"Base","Stress","Upside"},0),ASSUMPTIONS!$D$13,ASSUMPTIONS!$E$13,ASSUMPTIONS!$F$13) -> 900000 | I9: =ASSUMPTIONS!$B$13*CHOOSE(MATCH(ASSUMPTIONS!$B$7,{"Base","Stress","Upside"},0),ASSUMPTIONS!$D$13,ASSUMPTIONS!$E$13,ASSUMPTIONS!$F$13) -> 900000 | J9: =ASSUMPTIONS!$B$13*CHOOSE(MATCH(ASSUMPTIONS!$B$7,{"Base","Stress","Upside"},0),ASSUMPTIONS!$D$13,ASSUMPTIONS!$E$13,ASSUMPTIONS!$F$13) -> 900000 | ... O9: =ASSUMPTIONS!$B$13*CHOOSE(MATCH(ASSUMPTIONS!$B$7,{"Base","Stress","Upside"},0),ASSUMPTIONS!$D$13,ASSUMPTIONS!$E$13,ASSUMPTIONS!$F$13) -> 900000 | P9: =SUM(C9:O9) -> 11700000
A10: Loan Drawdowns | B10: Enter one-off receipts in weekly cells below (blue cells) | C10: 0 | D10: 0 | E10: 0 | F10: 0 | G10: 0 | H10: 0 | I10: 0 | J10: 0 | K10: 0 | L10: 0 | M10: 0 | N10: 0 | O10: 0 | P10: =SUM(C10:O10) -> 0
A11: Other Income | B11: VAT refunds, rebates, interest received | C11: =ASSUMPTIONS!$B$15*CHOOSE(MATCH(ASSUMPTIONS!$B$7,{"Base","Stress","Upside"},0),ASSUMPTIONS!$D$15,ASSUMPTIONS!$E$15,ASSUMPTIONS!$F$15) -> 50000 | D11: =ASSUMPTIONS!$B$15*CHOOSE(MATCH(ASSUMPTIONS!$B$7,{"Base","Stress","Upside"},0),ASSUMPTIONS!$D$15,ASSUMPTIONS!$E$15,ASSUMPTIONS!$F$15) -> 50000 | E11: =ASSUMPTIONS!$B$15*CHOOSE(MATCH(ASSUMPTIONS!$B$7,{"Base","Stress","Upside"},0),ASSUMPTIONS!$D$15,ASSUMPTIONS!$E$15,ASSUMPTIONS!$F$15) -> 50000 | F11: =ASSUMPTIONS!$B$15*CHOOSE(MATCH(ASSUMPTIONS!$B$7,{"Base","Stress","Upside"},0),ASSUMPTIONS!$D$15,ASSUMPTIONS!$E$15,ASSUMPTIONS!$F$15) -> 50000 | G11: =ASSUMPTIONS!$B$15*CHOOSE(MATCH(ASSUMPTIONS!$B$7,{"Base","Stress","Upside"},0),ASSUMPTIONS!$D$15,ASSUMPTIONS!$E$15,ASSUMPTIONS!$F$15) -> 50000 | H11: =ASSUMPTIONS!$B$15*CHOOSE(MATCH(ASSUMPTIONS!$B$7,{"Base","Stress","Upside"},0),ASSUMPTIONS!$D$15,ASSUMPTIONS!$E$15,ASSUMPTIONS!$F$15) -> 50000 | I11: =ASSUMPTIONS!$B$15*CHOOSE(MATCH(ASSUMPTIONS!$B$7,{"Base","Stress","Upside"},0),ASSUMPTIONS!$D$15,ASSUMPTIONS!$E$15,ASSUMPTIONS!$F$15) -> 50000 | J11: =ASSUMPTIONS!$B$15*CHOOSE(MATCH(ASSUMPTIONS!$B$7,{"Base","Stress","Upside"},0),ASSUMPTIONS!$D$15,ASSUMPTIONS!$E$15,ASSUMPTIONS!$F$15) -> 50000 | ... O11: =ASSUMPTIONS!$B$15*CHOOSE(MATCH(ASSUMPTIONS!$B$7,{"Base","Stress","Upside"},0),ASSUMPTIONS!$D$15,ASSUMPTIONS!$E$15,ASSUMPTIONS!$F$15) -> 50000 | P11: =SUM(C11:O11) -> 650000
A12: TOTAL INFLOWS | C12: =SUM(C9:C11) -> 950000 | D12: =SUM(D9:D11) -> 950000 | E12: =SUM(E9:E11) -> 950000 | F12: =SUM(F9:F11) -> 950000 | G12: =SUM(G9:G11) -> 950000 | H12: =SUM(H9:H11) -> 950000 | I12: =SUM(I9:I11) -> 950000 | J12: =SUM(J9:J11) -> 950000 | ... O12: =SUM(O9:O11) -> 950000 | P12: =SUM(C12:O12) -> 12350000
A13: OUTFLOWS
A14: Suppliers / Stock Purchases | B14: Payments to trade creditors | C14: =ASSUMPTIONS!$B$19*CHOOSE(MATCH(ASSUMPTIONS!$B$7,{"Base","Stress","Upside"},0),ASSUMPTIONS!$D$19,ASSUMPTIONS!$E$19,ASSUMPTIONS!$F$19) -> 420000 | D14: =ASSUMPTIONS!$B$19*CHOOSE(MATCH(ASSUMPTIONS!$B$7,{"Base","Stress","Upside"},0),ASSUMPTIONS!$D$19,ASSUMPTIONS!$E$19,ASSUMPTIONS!$F$19) -> 420000 | E14: =ASSUMPTIONS!$B$19*CHOOSE(MATCH(ASSUMPTIONS!$B$7,{"Base","Stress","Upside"},0),ASSUMPTIONS!$D$19,ASSUMPTIONS!$E$19,ASSUMPTIONS!$F$19) -> 420000 | F14: =ASSUMPTIONS!$B$19*CHOOSE(MATCH(ASSUMPTIONS!$B$7,{"Base","Stress","Upside"},0),ASSUMPTIONS!$D$19,ASSUMPTIONS!$E$19,ASSUMPTIONS!$F$19) -> 420000 | G14: =ASSUMPTIONS!$B$19*CHOOSE(MATCH(ASSUMPTIONS!$B$7,{"Base","Stress","Upside"},0),ASSUMPTIONS!$D$19,ASSUMPTIONS!$E$19,ASSUMPTIONS!$F$19) -> 420000 | H14: =ASSUMPTIONS!$B$19*CHOOSE(MATCH(ASSUMPTIONS!$B$7,{"Base","Stress","Upside"},0),ASSUMPTIONS!$D$19,ASSUMPTIONS!$E$19,ASSUMPTIONS!$F$19) -> 420000 | I14: =ASSUMPTIONS!$B$19*CHOOSE(MATCH(ASSUMPTIONS!$B$7,{"Base","Stress","Upside"},0),ASSUMPTIONS!$D$19,ASSUMPTIONS!$E$19,ASSUMPTIONS!$F$19) -> 420000 | J14: =ASSUMPTIONS!$B$19*CHOOSE(MATCH(ASSUMPTIONS!$B$7,{"Base","Stress","Upside"},0),ASSUMPTIONS!$D$19,ASSUMPTIONS!$E$19,ASSUMPTIONS!$F$19) -> 420000 | ... O14: =ASSUMPTIONS!$B$19*CHOOSE(MATCH(ASSUMPTIONS!$B$7,{"Base","Stress","Upside"},0),ASSUMPTIONS!$D$19,ASSUMPTIONS!$E$19,ASSUMPTIONS!$F$19) -> 420000 | P14: =SUM(C14:O14) -> 5460000
A15: Salaries & Wages | B15: KES 250K/month spread over 4 weeks | C15: =ASSUMPTIONS!$B$20*CHOOSE(MATCH(ASSUMPTIONS!$B$7,{"Base","Stress","Upside"},0),ASSUMPTIONS!$D$20,ASSUMPTIONS!$E$20,ASSUMPTIONS!$F$20) -> 62500 | D15: =ASSUMPTIONS!$B$20*CHOOSE(MATCH(ASSUMPTIONS!$B$7,{"Base","Stress","Upside"},0),ASSUMPTIONS!$D$20,ASSUMPTIONS!$E$20,ASSUMPTIONS!$F$20) -> 62500 | E15: =ASSUMPTIONS!$B$20*CHOOSE(MATCH(ASSUMPTIONS!$B$7,{"Base","Stress","Upside"},0),ASSUMPTIONS!$D$20,ASSUMPTIONS!$E$20,ASSUMPTIONS!$F$20) -> 62500 | F15: =ASSUMPTIONS!$B$20*CHOOSE(MATCH(ASSUMPTIONS!$B$7,{"Base","Stress","Upside"},0),ASSUMPTIONS!$D$20,ASSUMPTIONS!$E$20,ASSUMPTIONS!$F$20) -> 62500 | G15: =ASSUMPTIONS!$B$20*CHOOSE(MATCH(ASSUMPTIONS!$B$7,{"Base","Stress","Upside"},0),ASSUMPTIONS!$D$20,ASSUMPTIONS!$E$20,ASSUMPTIONS!$F$20) -> 62500 | H15: =ASSUMPTIONS!$B$20*CHOOSE(MATCH(ASSUMPTIONS!$B$7,{"Base","Stress","Upside"},0),ASSUMPTIONS!$D$20,ASSUMPTIONS!$E$20,ASSUMPTIONS!$F$20) -> 62500 | I15: =ASSUMPTIONS!$B$20*CHOOSE(MATCH(ASSUMPTIONS!$B$7,{"Base","Stress","Upside"},0),ASSUMPTIONS!$D$20,ASSUMPTIONS!$E$20,ASSUMPTIONS!$F$20) -> 62500 | J15: =ASSUMPTIONS!$B$20*CHOOSE(MATCH(ASSUMPTIONS!$B$7,{"Base","Stress","Upside"},0),ASSUMPTIONS!$D$20,ASSUMPTIONS!$E$20,ASSUMPTIONS!$F$20) -> 62500 | ... O15: =ASSUMPTIONS!$B$20*CHOOSE(MATCH(ASSUMPTIONS!$B$7,{"Base","Stress","Upside"},0),ASSUMPTIONS!$D$20,ASSUMPTIONS!$E$20,ASSUMPTIONS!$F$20) -> 62500 | P15: =SUM(C15:O15) -> 812500
A16: PAYE Remittance | B16: Avg KES 45K/month. KRA due 9th of following month | C16: =ASSUMPTIONS!$B$21*CHOOSE(MATCH(ASSUMPTIONS!$B$7,{"Base","Stress","Upside"},0),ASSUMPTIONS!$D$21,ASSUMPTIONS!$E$21,ASSUMPTIONS!$F$21) -> 11250 | D16: =ASSUMPTIONS!$B$21*CHOOSE(MATCH(ASSUMPTIONS!$B$7,{"Base","Stress","Upside"},0),ASSUMPTIONS!$D$21,ASSUMPTIONS!$E$21,ASSUMPTIONS!$F$21) -> 11250 | E16: =ASSUMPTIONS!$B$21*CHOOSE(MATCH(ASSUMPTIONS!$B$7,{"Base","Stress","Upside"},0),ASSUMPTIONS!$D$21,ASSUMPTIONS!$E$21,ASSUMPTIONS!$F$21) -> 11250 | F16: =ASSUMPTIONS!$B$21*CHOOSE(MATCH(ASSUMPTIONS!$B$7,{"Base","Stress","Upside"},0),ASSUMPTIONS!$D$21,ASSUMPTIONS!$E$21,ASSUMPTIONS!$F$21) -> 11250 | G16: =ASSUMPTIONS!$B$21*CHOOSE(MATCH(ASSUMPTIONS!$B$7,{"Base","Stress","Upside"},0),ASSUMPTIONS!$D$21,ASSUMPTIONS!$E$21,ASSUMPTIONS!$F$21) -> 11250 | H16: =ASSUMPTIONS!$B$21*CHOOSE(MATCH(ASSUMPTIONS!$B$7,{"Base","Stress","Upside"},0),ASSUMPTIONS!$D$21,ASSUMPTIONS!$E$21,ASSUMPTIONS!$F$21) -> 11250 | I16: =ASSUMPTIONS!$B$21*CHOOSE(MATCH(ASSUMPTIONS!$B$7,{"Base","Stress","Upside"},0),ASSUMPTIONS!$D$21,ASSUMPTIONS!$E$21,ASSUMPTIONS!$F$21) -> 11250 | J16: =ASSUMPTIONS!$B$21*CHOOSE(MATCH(ASSUMPTIONS!$B$7,{"Base","Stress","Upside"},0),ASSUMPTIONS!$D$21,ASSUMPTIONS!$E$21,ASSUMPTIONS!$F$21) -> 11250 | ... O16: =ASSUMPTIONS!$B$21*CHOOSE(MATCH(ASSUMPTIONS!$B$7,{"Base","Stress","Upside"},0),ASSUMPTIONS!$D$21,ASSUMPTIONS!$E$21,ASSUMPTIONS!$F$21) -> 11250 | P16: =SUM(C16:O16) -> 146250
A17: VAT Remittance | B17: Avg KES 90K/month. KRA due 20th of following month | C17: =ASSUMPTIONS!$B$22*CHOOSE(MATCH(ASSUMPTIONS!$B$7,{"Base","Stress","Upside"},0),ASSUMPTIONS!$D$22,ASSUMPTIONS!$E$22,ASSUMPTIONS!$F$22) -> 22500 | D17: =ASSUMPTIONS!$B$22*CHOOSE(MATCH(ASSUMPTIONS!$B$7,{"Base","Stress","Upside"},0),ASSUMPTIONS!$D$22,ASSUMPTIONS!$E$22,ASSUMPTIONS!$F$22) -> 22500 | E17: =ASSUMPTIONS!$B$22*CHOOSE(MATCH(ASSUMPTIONS!$B$7,{"Base","Stress","Upside"},0),ASSUMPTIONS!$D$22,ASSUMPTIONS!$E$22,ASSUMPTIONS!$F$22) -> 22500 | F17: =ASSUMPTIONS!$B$22*CHOOSE(MATCH(ASSUMPTIONS!$B$7,{"Base","Stress","Upside"},0),ASSUMPTIONS!$D$22,ASSUMPTIONS!$E$22,ASSUMPTIONS!$F$22) -> 22500 | G17: =ASSUMPTIONS!$B$22*CHOOSE(MATCH(ASSUMPTIONS!$B$7,{"Base","Stress","Upside"},0),ASSUMPTIONS!$D$22,ASSUMPTIONS!$E$22,ASSUMPTIONS!$F$22) -> 22500 | H17: =ASSUMPTIONS!$B$22*CHOOSE(MATCH(ASSUMPTIONS!$B$7,{"Base","Stress","Upside"},0),ASSUMPTIONS!$D$22,ASSUMPTIONS!$E$22,ASSUMPTIONS!$F$22) -> 22500 | I17: =ASSUMPTIONS!$B$22*CHOOSE(MATCH(ASSUMPTIONS!$B$7,{"Base","Stress","Upside"},0),ASSUMPTIONS!$D$22,ASSUMPTIONS!$E$22,ASSUMPTIONS!$F$22) -> 22500 | J17: =ASSUMPTIONS!$B$22*CHOOSE(MATCH(ASSUMPTIONS!$B$7,{"Base","Stress","Upside"},0),ASSUMPTIONS!$D$22,ASSUMPTIONS!$E$22,ASSUMPTIONS!$F$22) -> 22500 | ... O17: =ASSUMPTIONS!$B$22*CHOOSE(MATCH(ASSUMPTIONS!$B$7,{"Base","Stress","Upside"},0),ASSUMPTIONS!$D$22,ASSUMPTIONS!$E$22,ASSUMPTIONS!$F$22) -> 22500 | P17: =SUM(C17:O17) -> 292500
A18: NSSF Contributions | B18: Employee & employer share. Due month-end | C18: =ASSUMPTIONS!$B$23*CHOOSE(MATCH(ASSUMPTIONS!$B$7,{"Base","Stress","Upside"},0),ASSUMPTIONS!$D$23,ASSUMPTIONS!$E$23,ASSUMPTIONS!$F$23) -> 3000 | D18: =ASSUMPTIONS!$B$23*CHOOSE(MATCH(ASSUMPTIONS!$B$7,{"Base","Stress","Upside"},0),ASSUMPTIONS!$D$23,ASSUMPTIONS!$E$23,ASSUMPTIONS!$F$23) -> 3000 | E18: =ASSUMPTIONS!$B$23*CHOOSE(MATCH(ASSUMPTIONS!$B$7,{"Base","Stress","Upside"},0),ASSUMPTIONS!$D$23,ASSUMPTIONS!$E$23,ASSUMPTIONS!$F$23) -> 3000 | F18: =ASSUMPTIONS!$B$23*CHOOSE(MATCH(ASSUMPTIONS!$B$7,{"Base","Stress","Upside"},0),ASSUMPTIONS!$D$23,ASSUMPTIONS!$E$23,ASSUMPTIONS!$F$23) -> 3000 | G18: =ASSUMPTIONS!$B$23*CHOOSE(MATCH(ASSUMPTIONS!$B$7,{"Base","Stress","Upside"},0),ASSUMPTIONS!$D$23,ASSUMPTIONS!$E$23,ASSUMPTIONS!$F$23) -> 3000 | H18: =ASSUMPTIONS!$B$23*CHOOSE(MATCH(ASSUMPTIONS!$B$7,{"Base","Stress","Upside"},0),ASSUMPTIONS!$D$23,ASSUMPTIONS!$E$23,ASSUMPTIONS!$F$23) -> 3000 | I18: =ASSUMPTIONS!$B$23*CHOOSE(MATCH(ASSUMPTIONS!$B$7,{"Base","Stress","Upside"},0),ASSUMPTIONS!$D$23,ASSUMPTIONS!$E$23,ASSUMPTIONS!$F$23) -> 3000 | J18: =ASSUMPTIONS!$B$23*CHOOSE(MATCH(ASSUMPTIONS!$B$7,{"Base","Stress","Upside"},0),ASSUMPTIONS!$D$23,ASSUMPTIONS!$E$23,ASSUMPTIONS!$F$23) -> 3000 | ... O18: =ASSUMPTIONS!$B$23*CHOOSE(MATCH(ASSUMPTIONS!$B$7,{"Base","Stress","Upside"},0),ASSUMPTIONS!$D$23,ASSUMPTIONS!$E$23,ASSUMPTIONS!$F$23) -> 3000 | P18: =SUM(C18:O18) -> 39000
A19: NHIF / SHIF Contributions | B19: Social health insurance. Due month-end | C19: =ASSUMPTIONS!$B$24*CHOOSE(MATCH(ASSUMPTIONS!$B$7,{"Base","Stress","Upside"},0),ASSUMPTIONS!$D$24,ASSUMPTIONS!$E$24,ASSUMPTIONS!$F$24) -> 3750 | D19: =ASSUMPTIONS!$B$24*CHOOSE(MATCH(ASSUMPTIONS!$B$7,{"Base","Stress","Upside"},0),ASSUMPTIONS!$D$24,ASSUMPTIONS!$E$24,ASSUMPTIONS!$F$24) -> 3750 | E19: =ASSUMPTIONS!$B$24*CHOOSE(MATCH(ASSUMPTIONS!$B$7,{"Base","Stress","Upside"},0),ASSUMPTIONS!$D$24,ASSUMPTIONS!$E$24,ASSUMPTIONS!$F$24) -> 3750 | F19: =ASSUMPTIONS!$B$24*CHOOSE(MATCH(ASSUMPTIONS!$B$7,{"Base","Stress","Upside"},0),ASSUMPTIONS!$D$24,ASSUMPTIONS!$E$24,ASSUMPTIONS!$F$24) -> 3750 | G19: =ASSUMPTIONS!$B$24*CHOOSE(MATCH(ASSUMPTIONS!$B$7,{"Base","Stress","Upside"},0),ASSUMPTIONS!$D$24,ASSUMPTIONS!$E$24,ASSUMPTIONS!$F$24) -> 3750 | H19: =ASSUMPTIONS!$B$24*CHOOSE(MATCH(ASSUMPTIONS!$B$7,{"Base","Stress","Upside"},0),ASSUMPTIONS!$D$24,ASSUMPTIONS!$E$24,ASSUMPTIONS!$F$24) -> 3750 | I19: =ASSUMPTIONS!$B$24*CHOOSE(MATCH(ASSUMPTIONS!$B$7,{"Base","Stress","Upside"},0),ASSUMPTIONS!$D$24,ASSUMPTIONS!$E$24,ASSUMPTIONS!$F$24) -> 3750 | J19: =ASSUMPTIONS!$B$24*CHOOSE(MATCH(ASSUMPTIONS!$B$7,{"Base","Stress","Upside"},0),ASSUMPTIONS!$D$24,ASSUMPTIONS!$E$24,ASSUMPTIONS!$F$24) -> 3750 | ... O19: =ASSUMPTIONS!$B$24*CHOOSE(MATCH(ASSUMPTIONS!$B$7,{"Base","Stress","Upside"},0),ASSUMPTIONS!$D$24,ASSUMPTIONS!$E$24,ASSUMPTIONS!$F$24) -> 3750 | P19: =SUM(C19:O19) -> 48750
A20: Rent | B20: Avg KES 85K/month. Paid at start of month | C20: =ASSUMPTIONS!$B$25*CHOOSE(MATCH(ASSUMPTIONS!$B$7,{"Base","Stress","Upside"},0),ASSUMPTIONS!$D$25,ASSUMPTIONS!$E$25,ASSUMPTIONS!$F$25) -> 21250 | D20: =ASSUMPTIONS!$B$25*CHOOSE(MATCH(ASSUMPTIONS!$B$7,{"Base","Stress","Upside"},0),ASSUMPTIONS!$D$25,ASSUMPTIONS!$E$25,ASSUMPTIONS!$F$25) -> 21250 | E20: =ASSUMPTIONS!$B$25*CHOOSE(MATCH(ASSUMPTIONS!$B$7,{"Base","Stress","Upside"},0),ASSUMPTIONS!$D$25,ASSUMPTIONS!$E$25,ASSUMPTIONS!$F$25) -> 21250 | F20: =ASSUMPTIONS!$B$25*CHOOSE(MATCH(ASSUMPTIONS!$B$7,{"Base","Stress","Upside"},0),ASSUMPTIONS!$D$25,ASSUMPTIONS!$E$25,ASSUMPTIONS!$F$25) -> 21250 | G20: =ASSUMPTIONS!$B$25*CHOOSE(MATCH(ASSUMPTIONS!$B$7,{"Base","Stress","Upside"},0),ASSUMPTIONS!$D$25,ASSUMPTIONS!$E$25,ASSUMPTIONS!$F$25) -> 21250 | H20: =ASSUMPTIONS!$B$25*CHOOSE(MATCH(ASSUMPTIONS!$B$7,{"Base","Stress","Upside"},0),ASSUMPTIONS!$D$25,ASSUMPTIONS!$E$25,ASSUMPTIONS!$F$25) -> 21250 | I20: =ASSUMPTIONS!$B$25*CHOOSE(MATCH(ASSUMPTIONS!$B$7,{"Base","Stress","Upside"},0),ASSUMPTIONS!$D$25,ASSUMPTIONS!$E$25,ASSUMPTIONS!$F$25) -> 21250 | J20: =ASSUMPTIONS!$B$25*CHOOSE(MATCH(ASSUMPTIONS!$B$7,{"Base","Stress","Upside"},0),ASSUMPTIONS!$D$25,ASSUMPTIONS!$E$25,ASSUMPTIONS!$F$25) -> 21250 | ... O20: =ASSUMPTIONS!$B$25*CHOOSE(MATCH(ASSUMPTIONS!$B$7,{"Base","Stress","Upside"},0),ASSUMPTIONS!$D$25,ASSUMPTIONS!$E$25,ASSUMPTIONS!$F$25) -> 21250 | P20: =SUM(C20:O20) -> 276250
A21: Utilities | B21: Electricity, water, internet | C21: =ASSUMPTIONS!$B$26*CHOOSE(MATCH(ASSUMPTIONS!$B$7,{"Base","Stress","Upside"},0),ASSUMPTIONS!$D$26,ASSUMPTIONS!$E$26,ASSUMPTIONS!$F$26) -> 25000 | D21: =ASSUMPTIONS!$B$26*CHOOSE(MATCH(ASSUMPTIONS!$B$7,{"Base","Stress","Upside"},0),ASSUMPTIONS!$D$26,ASSUMPTIONS!$E$26,ASSUMPTIONS!$F$26) -> 25000 | E21: =ASSUMPTIONS!$B$26*CHOOSE(MATCH(ASSUMPTIONS!$B$7,{"Base","Stress","Upside"},0),ASSUMPTIONS!$D$26,ASSUMPTIONS!$E$26,ASSUMPTIONS!$F$26) -> 25000 | F21: =ASSUMPTIONS!$B$26*CHOOSE(MATCH(ASSUMPTIONS!$B$7,{"Base","Stress","Upside"},0),ASSUMPTIONS!$D$26,ASSUMPTIONS!$E$26,ASSUMPTIONS!$F$26) -> 25000 | G21: =ASSUMPTIONS!$B$26*CHOOSE(MATCH(ASSUMPTIONS!$B$7,{"Base","Stress","Upside"},0),ASSUMPTIONS!$D$26,ASSUMPTIONS!$E$26,ASSUMPTIONS!$F$26) -> 25000 | H21: =ASSUMPTIONS!$B$26*CHOOSE(MATCH(ASSUMPTIONS!$B$7,{"Base","Stress","Upside"},0),ASSUMPTIONS!$D$26,ASSUMPTIONS!$E$26,ASSUMPTIONS!$F$26) -> 25000 | I21: =ASSUMPTIONS!$B$26*CHOOSE(MATCH(ASSUMPTIONS!$B$7,{"Base","Stress","Upside"},0),ASSUMPTIONS!$D$26,ASSUMPTIONS!$E$26,ASSUMPTIONS!$F$26) -> 25000 | J21: =ASSUMPTIONS!$B$26*CHOOSE(MATCH(ASSUMPTIONS!$B$7,{"Base","Stress","Upside"},0),ASSUMPTIONS!$D$26,ASSUMPTIONS!$E$26,ASSUMPTIONS!$F$26) -> 25000 | ... O21: =ASSUMPTIONS!$B$26*CHOOSE(MATCH(ASSUMPTIONS!$B$7,{"Base","Stress","Upside"},0),ASSUMPTIONS!$D$26,ASSUMPTIONS!$E$26,ASSUMPTIONS!$F$26) -> 25000 | P21: =SUM(C21:O21) -> 325000
A22: Loan Repayments | B22: Avg KES 60K/month. Bank instalment | C22: =ASSUMPTIONS!$B$27*CHOOSE(MATCH(ASSUMPTIONS!$B$7,{"Base","Stress","Upside"},0),ASSUMPTIONS!$D$27,ASSUMPTIONS!$E$27,ASSUMPTIONS!$F$27) -> 15000 | D22: =ASSUMPTIONS!$B$27*CHOOSE(MATCH(ASSUMPTIONS!$B$7,{"Base","Stress","Upside"},0),ASSUMPTIONS!$D$27,ASSUMPTIONS!$E$27,ASSUMPTIONS!$F$27) -> 15000 | E22: =ASSUMPTIONS!$B$27*CHOOSE(MATCH(ASSUMPTIONS!$B$7,{"Base","Stress","Upside"},0),ASSUMPTIONS!$D$27,ASSUMPTIONS!$E$27,ASSUMPTIONS!$F$27) -> 15000 | F22: =ASSUMPTIONS!$B$27*CHOOSE(MATCH(ASSUMPTIONS!$B$7,{"Base","Stress","Upside"},0),ASSUMPTIONS!$D$27,ASSUMPTIONS!$E$27,ASSUMPTIONS!$F$27) -> 15000 | G22: =ASSUMPTIONS!$B$27*CHOOSE(MATCH(ASSUMPTIONS!$B$7,{"Base","Stress","Upside"},0),ASSUMPTIONS!$D$27,ASSUMPTIONS!$E$27,ASSUMPTIONS!$F$27) -> 15000 | H22: =ASSUMPTIONS!$B$27*CHOOSE(MATCH(ASSUMPTIONS!$B$7,{"Base","Stress","Upside"},0),ASSUMPTIONS!$D$27,ASSUMPTIONS!$E$27,ASSUMPTIONS!$F$27) -> 15000 | I22: =ASSUMPTIONS!$B$27*CHOOSE(MATCH(ASSUMPTIONS!$B$7,{"Base","Stress","Upside"},0),ASSUMPTIONS!$D$27,ASSUMPTIONS!$E$27,ASSUMPTIONS!$F$27) -> 15000 | J22: =ASSUMPTIONS!$B$27*CHOOSE(MATCH(ASSUMPTIONS!$B$7,{"Base","Stress","Upside"},0),ASSUMPTIONS!$D$27,ASSUMPTIONS!$E$27,ASSUMPTIONS!$F$27) -> 15000 | ... O22: =ASSUMPTIONS!$B$27*CHOOSE(MATCH(ASSUMPTIONS!$B$7,{"Base","Stress","Upside"},0),ASSUMPTIONS!$D$27,ASSUMPTIONS!$E$27,ASSUMPTIONS!$F$27) -> 15000 | P22: =SUM(C22:O22) -> 195000
A23: Other Overheads | B23: Admin, transport, sundry expenses | C23: =ASSUMPTIONS!$B$28*CHOOSE(MATCH(ASSUMPTIONS!$B$7,{"Base","Stress","Upside"},0),ASSUMPTIONS!$D$28,ASSUMPTIONS!$E$28,ASSUMPTIONS!$F$28) -> 35000 | D23: =ASSUMPTIONS!$B$28*CHOOSE(MATCH(ASSUMPTIONS!$B$7,{"Base","Stress","Upside"},0),ASSUMPTIONS!$D$28,ASSUMPTIONS!$E$28,ASSUMPTIONS!$F$28) -> 35000 | E23: =ASSUMPTIONS!$B$28*CHOOSE(MATCH(ASSUMPTIONS!$B$7,{"Base","Stress","Upside"},0),ASSUMPTIONS!$D$28,ASSUMPTIONS!$E$28,ASSUMPTIONS!$F$28) -> 35000 | F23: =ASSUMPTIONS!$B$28*CHOOSE(MATCH(ASSUMPTIONS!$B$7,{"Base","Stress","Upside"},0),ASSUMPTIONS!$D$28,ASSUMPTIONS!$E$28,ASSUMPTIONS!$F$28) -> 35000 | G23: =ASSUMPTIONS!$B$28*CHOOSE(MATCH(ASSUMPTIONS!$B$7,{"Base","Stress","Upside"},0),ASSUMPTIONS!$D$28,ASSUMPTIONS!$E$28,ASSUMPTIONS!$F$28) -> 35000 | H23: =ASSUMPTIONS!$B$28*CHOOSE(MATCH(ASSUMPTIONS!$B$7,{"Base","Stress","Upside"},0),ASSUMPTIONS!$D$28,ASSUMPTIONS!$E$28,ASSUMPTIONS!$F$28) -> 35000 | I23: =ASSUMPTIONS!$B$28*CHOOSE(MATCH(ASSUMPTIONS!$B$7,{"Base","Stress","Upside"},0),ASSUMPTIONS!$D$28,ASSUMPTIONS!$E$28,ASSUMPTIONS!$F$28) -> 35000 | J23: =ASSUMPTIONS!$B$28*CHOOSE(MATCH(ASSUMPTIONS!$B$7,{"Base","Stress","Upside"},0),ASSUMPTIONS!$D$28,ASSUMPTIONS!$E$28,ASSUMPTIONS!$F$28) -> 35000 | ... O23: =ASSUMPTIONS!$B$28*CHOOSE(MATCH(ASSUMPTIONS!$B$7,{"Base","Stress","Upside"},0),ASSUMPTIONS!$D$28,ASSUMPTIONS!$E$28,ASSUMPTIONS!$F$28) -> 35000 | P23: =SUM(C23:O23) -> 455000
A24: TOTAL OUTFLOWS | C24: =SUM(C14:C23) -> 619250 | D24: =SUM(D14:D23) -> 619250 | E24: =SUM(E14:E23) -> 619250 | F24: =SUM(F14:F23) -> 619250 | G24: =SUM(G14:G23) -> 619250 | H24: =SUM(H14:H23) -> 619250 | I24: =SUM(I14:I23) -> 619250 | J24: =SUM(J14:J23) -> 619250 | ... O24: =SUM(O14:O23) -> 619250 | P24: =SUM(C24:O24) -> 8050250
A25: NET CASH MOVEMENT | C25: =C12-C24 -> 330750 | D25: =D12-D24 -> 330750 | E25: =E12-E24 -> 330750 | F25: =F12-F24 -> 330750 | G25: =G12-G24 -> 330750 | H25: =H12-H24 -> 330750 | I25: =I12-I24 -> 330750 | J25: =J12-J24 -> 330750 | ... O25: =O12-O24 -> 330750 | P25: =SUM(C25:O25) -> 4299750
A26: CLOSING BALANCE | C26: =C7+C25 -> 1180750 | D26: =D7+D25 -> 1511500 | E26: =E7+E25 -> 1842250 | F26: =F7+F25 -> 2173000 | G26: =G7+G25 -> 2503750 | H26: =H7+H25 -> 2834500 | I26: =I7+I25 -> 3165250 | J26: =J7+J25 -> 3496000 | ... O26: =O7+O25 -> 5149750 | P26: =O26 -> 5149750
A28: Remittance timing note: Weekly amounts shown are normalized averages. PAYE is due to KRA by the 9th of the following month; VAT by the 20th; NSSF and NHIF/SHIF by the last day of the month. Adjust actual week input cells for client-specific timing if required.

Sheet DASHBOARD
B2: CASH FLOW DASHBOARD
B3: =ASSUMPTIONS!$B$7&" Scenario | Naicents Ltd" -> Base Scenario | Naicents Ltd
R4: Week | S4: Closing Balance (KES)
B5: KEY METRICS | R5: Wk 1 | S5: =CASHFLOW!C26 -> 1180750
B6: Opening Balance (KES) | E6: 13-Week Closing Balance (KES) | H6: Minimum Weekly Balance (KES) | K6: Total Net Movement (KES) | R6: Wk 2 | S6: =CASHFLOW!D26 -> 1511500
B7: =CASHFLOW!C7 -> 850000 | E7: =CASHFLOW!O26 -> 5149750 | H7: =MIN(CASHFLOW!C26:O26) -> 1180750 | K7: =CASHFLOW!P25 -> 4299750 | R7: Wk 3 | S7: =CASHFLOW!E26 -> 1842250
R8: Wk 4 | S8: =CASHFLOW!F26 -> 2173000
B9: =IF(MIN(CASHFLOW!C26:O26)<ASSUMPTIONS!$B$8,"WARNING: Cash balance falls below the minimum threshold of KES "& TEXT(ASSUMPTIONS!$B$8,"#,##0")&" in one or more weeks. Review outflow timing.","HEALTHY: Cash balance remains above the minimum threshold of KES "& TEXT(ASSUMPTIONS!$B$8,"#,##0")&" throughout the 13-week period.") -> HEALTHY: Cash balance remains above the minimum threshold of KES 500,000 throughout the 13-week period. | R9: Wk 5 | S9: =CASHFLOW!G26 -> 2503750
R10: Wk 6 | S10: =CASHFLOW!H26 -> 2834500
R11: Wk 7 | S11: =CASHFLOW!I26 -> 3165250
R12: Wk 8 | S12: =CASHFLOW!J26 -> 3496000
R13: Wk 9 | S13: =CASHFLOW!K26 -> 3826750
R14: Wk 10 | S14: =CASHFLOW!L26 -> 4157500
R15: Wk 11 | S15: =CASHFLOW!M26 -> 4488250
R16: Wk 12 | S16: =CASHFLOW!N26 -> 4819000
R17: Wk 13 | S17: =CASHFLOW!O26 -> 5149750
B31: SCENARIO COMPARISON (13-WEEK CLOSING BALANCE)
B32: Scenario | C32: End Balance (KES) | D32: Variance vs Base (KES) | E32: Interpretation
B33: Base | C33: =ASSUMPTIONS!$B$9+13*(ASSUMPTIONS!$B$13*ASSUMPTIONS!$D$13+ASSUMPTIONS!$B$15*ASSUMPTIONS!$D$15)-13*(ASSUMPTIONS!$B$19*ASSUMPTIONS!$D$19+ASSUMPTIONS!$B$20*ASSUMPTIONS!$D$20+ASSUMPTIONS!$B$21*ASSUMPTIONS!$D$21+ASSUMPTIONS!$B$22*ASSUMPTIONS!$D$22+ASSUMPTIONS!$B$23*ASSUMPTIONS!$D$23+ASSUMPTIONS!$B$24*ASSUMPTIONS!$D$24+ASSUMPTIONS!$B$25*ASSUMPTIONS!$D$25+ASSUMPTIONS!$B$26*ASSUMPTIONS!$D$26+ASSUMPTIONS!$B$27*ASSUMPTIONS!$D$27+ASSUMPTIONS!$B$28*ASSUMPTIONS!$D$28) -> 5149750 | D33: - | E33: Normal operations. Use as baseline planning scenario.
B34: Stress | C34: =ASSUMPTIONS!$B$9+13*(ASSUMPTIONS!$B$13*ASSUMPTIONS!$E$13+ASSUMPTIONS!$B$15*ASSUMPTIONS!$E$15)-13*(ASSUMPTIONS!$B$19*ASSUMPTIONS!$E$19+ASSUMPTIONS!$B$20*ASSUMPTIONS!$E$20+ASSUMPTIONS!$B$21*ASSUMPTIONS!$E$21+ASSUMPTIONS!$B$22*ASSUMPTIONS!$E$22+ASSUMPTIONS!$B$23*ASSUMPTIONS!$E$23+ASSUMPTIONS!$B$24*ASSUMPTIONS!$E$24+ASSUMPTIONS!$B$25*ASSUMPTIONS!$E$25+ASSUMPTIONS!$B$26*ASSUMPTIONS!$E$26+ASSUMPTIONS!$B$27*ASSUMPTIONS!$E$27+ASSUMPTIONS!$B$28*ASSUMPTIONS!$E$28) -> 853250 | D34: =C34-C33 -> -4296500 | E34: Revenue decline + cost pressure. Test for covenant and liquidity risk.
B35: Upside | C35: =ASSUMPTIONS!$B$9+13*(ASSUMPTIONS!$B$13*ASSUMPTIONS!$F$13+ASSUMPTIONS!$B$15*ASSUMPTIONS!$F$15)-13*(ASSUMPTIONS!$B$19*ASSUMPTIONS!$F$19+ASSUMPTIONS!$B$20*ASSUMPTIONS!$F$20+ASSUMPTIONS!$B$21*ASSUMPTIONS!$F$21+ASSUMPTIONS!$B$22*ASSUMPTIONS!$F$22+ASSUMPTIONS!$B$23*ASSUMPTIONS!$F$23+ASSUMPTIONS!$B$24*ASSUMPTIONS!$F$24+ASSUMPTIONS!$B$25*ASSUMPTIONS!$F$25+ASSUMPTIONS!$B$26*ASSUMPTIONS!$F$26+ASSUMPTIONS!$B$27*ASSUMPTIONS!$F$27+ASSUMPTIONS!$B$28*ASSUMPTIONS!$F$28) -> 8178750 | D35: =C35-C33 -> 3029000 | E35: Strong trading + cost efficiencies. Assess growth capacity.
