Workbook

Sheet Notes
B2: SA BREWERIES KENYA LTD — SOUTH AFRICAN WINE IMPORT MODEL
B3: Notes, methodology, and user guide
B5: PURPOSE
B6: This model evaluates the unit economics and monthly profitability of importing South African wine into Kenya for distribution across supermarkets, lodges, and hotels. It builds bottle-level landed cost from FOB through Kenyan customs duties, layers operating expenses, and applies channel-specific margins to project a monthly P&L.
B8: WHAT THE MODEL DEMONSTRATES
B9: 1. Full landed-cost build-up per SKU — FOB (ZAR) → CIF (KES) → Import Duty + Excise + IDF + RDL → VAT → Clearing & Handling, for 26 wines across Budget / Mid / Premium tiers.
B10: 2. ABV-based excise duty calculation per the Kenya Tax Laws Amendment Act 2024 (KES 22.50 per cl of pure alcohol), correctly differentiating wines by alcohol strength.
B11: 3. Channel pricing logic — supermarket, lodge/hotel, and suggested retail prices derived from landed cost + OpEx allocation + tier-specific margin (25% Budget / 30% Mid / 35% Premium).
B12: 4. Monthly P&L at 5,500 cases (66,000 bottles) showing revenue, COGS, gross profit, operating expenses, EBIT, and net profit after corporate tax.
B13: 5. Sensitivity analysis on the two highest-leverage variables: ZAR/KES exchange rate (drives landed cost) and monthly volume (drives OpEx absorption per bottle).
B15: HOW TO USE THE MODEL
B16: Step 1 — Update assumptions
... B29: SHEET MAP
B30: Sheet | C30: Purpose
B31: Assumptions | C31: FX rates, volume, Kenyan tax structure, freight & logistics rates
B32: Product Catalog & Landed Cost | C32: 26 SKUs with full duty/VAT build-up to landed cost per bottle
B33: Operating Expenses | C33: Monthly OpEx by category and per-bottle allocation
B34: Pricing Model | C34: Channel pricing by SKU — supermarket, lodge/hotel, retail, gross profit
B35: Monthly P&L | C35: Projected income statement at assumed volume
B36: Sensitivity Analysis | C36: FX and volume stress tests
B38: KEY ASSUMPTIONS TO VALIDATE
B39: • ZAR/KES spot rate — landed cost is highly sensitive (see Sensitivity sheet); refresh before any pricing decision.
B40: • Excise duty rate — currently KES 22.50/cl pure alcohol per 2024 Tax Laws Amendment; verify against latest KRA notice.
B41: • Monthly volume of 5,500 cases — the model assumes full absorption of fixed OpEx; below ~3,000 cases per-bottle OpEx rises sharply.
B42: • Margin tiers (25% / 30% / 35%) — these are target margins; actual realisation depends on negotiated trade terms with supermarkets and HORECA.
B43: • Freight assumptions are sea-freight defaults; switch to air-freight rates in Assumptions for premium/urgent shipments.
B45: COLOUR CODE
B46: Blue text | C46: Hardcoded inputs / assumptions you can change
B47: Black text | C47: Formulas and calculated values
B48: Green text | C48: Cross-sheet links pulling from another tab

Sheet Assumptions
B2: SA BREWERIES KENYA LTD - KEY ASSUMPTIONS
B4: FOREIGN EXCHANGE & GENERAL
B5: Parameter | C5: Value | D5: Unit | E5: Notes
B6: ZAR / KES Exchange Rate | C6: 7.2 | E6: Adjust to current spot rate
B7: USD / KES Exchange Rate | C7: 129.5 | E7: For USD-denominated freight
B8: Monthly Volume (cases of 12) | C8: 5500 | D8: cases | E8: 5,000+ target
B9: Bottles per Case | C9: 12 | D9: bottles | E9: Standard wine case
B10: Monthly Bottles | C10: =C8*C9 -> 66000 | D10: bottles | E10: Formula
B11: Standard Bottle Size | C11: 0.75 | D11: litres | E11: 750ml
B13: KENYAN IMPORT TAX STRUCTURE
B14: Tax / Levy | C14: Rate | D14: Basis | E14: Notes
B15: Import Duty | C15: 0.25 | D15: CIF Value | E15: EAC Common External Tariff for wine (HS 2204)
B16: Excise Duty | C16: 22.5 | D16: KES per cl of pure alcohol | E16: ABV-based method per Tax Laws Amendment Act 2024
B17: Import Declaration Fee (IDF) | C17: 0.035 | D17: CIF Value | E17: 3.5% of CIF
B18: Railway Development Levy (RDL) | C18: 0.02 | D18: CIF Value | E18: 2% of CIF
B19: VAT | C19: 0.16 | D19: CIF + Duties + Levies | E19: Standard 16% VAT
B21: FREIGHT & LOGISTICS (per case of 12)
B22: Cost Item | C22: Amount (KES) | D22: Unit | E22: Notes
B23: Sea Freight (Durban to Mombasa) | C23: 650 | D23: per case | E23: 20ft container ~1,200 cases
B24: Air Freight (Johannesburg to JKIA) | C24: 2800 | D24: per case | E24: For premium/urgent shipments
B25: Marine Insurance | C25: 0.015 | D25: % of FOB+Freight | E25: 1.5% standard
B26: Clearing & Forwarding Agent | C26: 350 | D26: per case | E26: Customs broker fees
B27: Port Charges / Handling | C27: 180 | D27: per case | E27: Mombasa or JKIA handling
B28: Inland Transport (Mombasa to Nairobi) | C28: 250 | D28: per case | E28: By SGR or road
B29: KEBS Inspection Fee | C29: 80 | D29: per case | E29: Standards compliance
B52: Corporate Income Tax Rate | C52: 0.3 | E52: KRA corporate tax rate

Sheet Product Catalog & Landed Cost
C2: PRODUCT CATALOG WITH LANDED COST CALCULATION (PER BOTTLE)
B4: # | C4: Wine Name | D4: Type | E4: ABV % | F4: Segment | G4: FOB/Bottle (ZAR) | H4: FOB/Bottle (KES) | I4: Freight/Bottle (KES) | J4: Insurance (KES) | K4: CIF/Bottle (KES) | L4: Import Duty (KES) | M4: Excise Duty (KES) | N4: IDF (KES) | O4: RDL (KES) | P4: Total Duties (KES) | Q4: VAT (KES) | R4: Clearing+Handling (KES) | S4: LANDED COST (KES)
B5: 1 | C5: Cape Valley Dry Red | D5: Red | E5: 0.13 | F5: Budget | G5: 28 | H5: =G5*Assumptions!$C$6 -> 201.6 | I5: =Assumptions!$C$23/12 -> 54.166667 | J5: =(H5+I5)*Assumptions!$C$25 -> 3.8365 | K5: =H5+I5+J5 -> 259.60317 | L5: =K5*Assumptions!$C$15 -> 64.900792 | M5: =E5*Assumptions!$C$11*100*Assumptions!$C$16 -> 219.375 | N5: =K5*Assumptions!$C$17 -> 9.0861108 | O5: =K5*Assumptions!$C$18 -> 5.1920633 | P5: =L5+M5+N5+O5 -> 298.55397 | Q5: =(K5+P5)*Assumptions!$C$19 -> 89.305141 | R5: =(Assumptions!$C$26+Assumptions!$C$27+Assumptions!$C$28+Assumptions!$C$29)/12 -> 71.666667 | S5: =K5+P5+Q5+R5 -> 719.12894
B6: 2 | C6: Cape Valley Sauvignon Blanc | D6: White | E6: 0.125 | F6: Budget | G6: 26 | H6: =G6*Assumptions!$C$6 -> 187.2 | I6: =Assumptions!$C$23/12 -> 54.166667 | J6: =(H6+I6)*Assumptions!$C$25 -> 3.6205 | K6: =H6+I6+J6 -> 244.98717 | L6: =K6*Assumptions!$C$15 -> 61.246792 | M6: =E6*Assumptions!$C$11*100*Assumptions!$C$16 -> 210.9375 | N6: =K6*Assumptions!$C$17 -> 8.5745508 | O6: =K6*Assumptions!$C$18 -> 4.8997433 | P6: =L6+M6+N6+O6 -> 285.65859 | Q6: =(K6+P6)*Assumptions!$C$19 -> 84.90332 | R6: =(Assumptions!$C$26+Assumptions!$C$27+Assumptions!$C$28+Assumptions!$C$29)/12 -> 71.666667 | S6: =K6+P6+Q6+R6 -> 687.21574
B7: 3 | C7: Cape Valley Rose | D7: Rose | E7: 0.12 | F7: Budget | G7: 27 | H7: =G7*Assumptions!$C$6 -> 194.4 | I7: =Assumptions!$C$23/12 -> 54.166667 | J7: =(H7+I7)*Assumptions!$C$25 -> 3.7285 | K7: =H7+I7+J7 -> 252.29517 | L7: =K7*Assumptions!$C$15 -> 63.073792 | M7: =E7*Assumptions!$C$11*100*Assumptions!$C$16 -> 202.5 | N7: =K7*Assumptions!$C$17 -> 8.8303308 | O7: =K7*Assumptions!$C$18 -> 5.0459033 | P7: =L7+M7+N7+O7 -> 279.45003 | Q7: =(K7+P7)*Assumptions!$C$19 -> 85.079231 | R7: =(Assumptions!$C$26+Assumptions!$C$27+Assumptions!$C$28+Assumptions!$C$29)/12 -> 71.666667 | S7: =K7+P7+Q7+R7 -> 688.49109
B8: 4 | C8: Vineyard Select Shiraz | D8: Red | E8: 0.135 | F8: Budget | G8: 35 | H8: =G8*Assumptions!$C$6 -> 252 | I8: =Assumptions!$C$23/12 -> 54.166667 | J8: =(H8+I8)*Assumptions!$C$25 -> 4.5925 | K8: =H8+I8+J8 -> 310.75917 | L8: =K8*Assumptions!$C$15 -> 77.689792 | M8: =E8*Assumptions!$C$11*100*Assumptions!$C$16 -> 227.8125 | N8: =K8*Assumptions!$C$17 -> 10.876571 | O8: =K8*Assumptions!$C$18 -> 6.2151833 | P8: =L8+M8+N8+O8 -> 322.59405 | Q8: =(K8+P8)*Assumptions!$C$19 -> 101.33651 | R8: =(Assumptions!$C$26+Assumptions!$C$27+Assumptions!$C$28+Assumptions!$C$29)/12 -> 71.666667 | S8: =K8+P8+Q8+R8 -> 806.35639
B9: 5 | C9: Vineyard Select Chenin Blanc | D9: White | E9: 0.13 | F9: Budget | G9: 33 | H9: =G9*Assumptions!$C$6 -> 237.6 | I9: =Assumptions!$C$23/12 -> 54.166667 | J9: =(H9+I9)*Assumptions!$C$25 -> 4.3765 | K9: =H9+I9+J9 -> 296.14317 | L9: =K9*Assumptions!$C$15 -> 74.035792 | M9: =E9*Assumptions!$C$11*100*Assumptions!$C$16 -> 219.375 | N9: =K9*Assumptions!$C$17 -> 10.365011 | O9: =K9*Assumptions!$C$18 -> 5.9228633 | P9: =L9+M9+N9+O9 -> 309.69867 | Q9: =(K9+P9)*Assumptions!$C$19 -> 96.934693 | R9: =(Assumptions!$C$26+Assumptions!$C$27+Assumptions!$C$28+Assumptions!$C$29)/12 -> 71.666667 | S9: =K9+P9+Q9+R9 -> 774.44319
B10: 6 | C10: Vineyard Select Dry Rose | D10: Rose | E10: 0.125 | F10: Budget | G10: 32 | H10: =G10*Assumptions!$C$6 -> 230.4 | I10: =Assumptions!$C$23/12 -> 54.166667 | J10: =(H10+I10)*Assumptions!$C$25 -> 4.2685 | K10: =H10+I10+J10 -> 288.83517 | L10: =K10*Assumptions!$C$15 -> 72.208792 | M10: =E10*Assumptions!$C$11*100*Assumptions!$C$16 -> 210.9375 | N10: =K10*Assumptions!$C$17 -> 10.109231 | O10: =K10*Assumptions!$C$18 -> 5.7767033 | P10: =L10+M10+N10+O10 -> 299.03223 | Q10: =(K10+P10)*Assumptions!$C$19 -> 94.058783 | R10: =(Assumptions!$C$26+Assumptions!$C$27+Assumptions!$C$28+Assumptions!$C$29)/12 -> 71.666667 | S10: =K10+P10+Q10+R10 -> 753.59284
B11: 7 | C11: Harvest Moon Pinotage | D11: Red | E11: 0.14 | F11: Budget | G11: 38 | H11: =G11*Assumptions!$C$6 -> 273.6 | I11: =Assumptions!$C$23/12 -> 54.166667 | J11: =(H11+I11)*Assumptions!$C$25 -> 4.9165 | K11: =H11+I11+J11 -> 332.68317 | L11: =K11*Assumptions!$C$15 -> 83.170792 | M11: =E11*Assumptions!$C$11*100*Assumptions!$C$16 -> 236.25 | N11: =K11*Assumptions!$C$17 -> 11.643911 | O11: =K11*Assumptions!$C$18 -> 6.6536633 | P11: =L11+M11+N11+O11 -> 337.71837 | Q11: =(K11+P11)*Assumptions!$C$19 -> 107.26425 | R11: =(Assumptions!$C$26+Assumptions!$C$27+Assumptions!$C$28+Assumptions!$C$29)/12 -> 71.666667 | S11: =K11+P11+Q11+R11 -> 849.33244
B12: 8 | C12: Harvest Moon Chardonnay | D12: White | E12: 0.13 | F12: Budget | G12: 36 | H12: =G12*Assumptions!$C$6 -> 259.2 | I12: =Assumptions!$C$23/12 -> 54.166667 | J12: =(H12+I12)*Assumptions!$C$25 -> 4.7005 | K12: =H12+I12+J12 -> 318.06717 | L12: =K12*Assumptions!$C$15 -> 79.516792 | M12: =E12*Assumptions!$C$11*100*Assumptions!$C$16 -> 219.375 | N12: =K12*Assumptions!$C$17 -> 11.132351 | O12: =K12*Assumptions!$C$18 -> 6.3613433 | P12: =L12+M12+N12+O12 -> 316.38549 | Q12: =(K12+P12)*Assumptions!$C$19 -> 101.51242 | R12: =(Assumptions!$C$26+Assumptions!$C$27+Assumptions!$C$28+Assumptions!$C$29)/12 -> 71.666667 | S12: =K12+P12+Q12+R12 -> 807.63174
B13: 9 | C13: Stellenbosch Hills Cabernet Sauvignon | D13: Red | E13: 0.14 | F13: Mid | G13: 55 | H13: =G13*Assumptions!$C$6 -> 396 | I13: =Assumptions!$C$23/12 -> 54.166667 | J13: =(H13+I13)*Assumptions!$C$25 -> 6.7525 | K13: =H13+I13+J13 -> 456.91917 | L13: =K13*Assumptions!$C$15 -> 114.22979 | M13: =E13*Assumptions!$C$11*100*Assumptions!$C$16 -> 236.25 | N13: =K13*Assumptions!$C$17 -> 15.992171 | O13: =K13*Assumptions!$C$18 -> 9.1383833 | P13: =L13+M13+N13+O13 -> 375.61035 | Q13: =(K13+P13)*Assumptions!$C$19 -> 133.20472 | R13: =(Assumptions!$C$26+Assumptions!$C$27+Assumptions!$C$28+Assumptions!$C$29)/12 -> 71.666667 | S13: =K13+P13+Q13+R13 -> 1037.4009
B14: 10 | C14: Stellenbosch Hills Merlot | D14: Red | E14: 0.135 | F14: Mid | G14: 52 | H14: =G14*Assumptions!$C$6 -> 374.4 | I14: =Assumptions!$C$23/12 -> 54.166667 | J14: =(H14+I14)*Assumptions!$C$25 -> 6.4285 | K14: =H14+I14+J14 -> 434.99517 | L14: =K14*Assumptions!$C$15 -> 108.74879 | M14: =E14*Assumptions!$C$11*100*Assumptions!$C$16 -> 227.8125 | N14: =K14*Assumptions!$C$17 -> 15.224831 | O14: =K14*Assumptions!$C$18 -> 8.6999033 | P14: =L14+M14+N14+O14 -> 360.48603 | Q14: =(K14+P14)*Assumptions!$C$19 -> 127.27699 | R14: =(Assumptions!$C$26+Assumptions!$C$27+Assumptions!$C$28+Assumptions!$C$29)/12 -> 71.666667 | S14: =K14+P14+Q14+R14 -> 994.42485
B15: 11 | C15: Robertson Valley Sauvignon Blanc | D15: White | E15: 0.13 | F15: Mid | G15: 48 | H15: =G15*Assumptions!$C$6 -> 345.6 | I15: =Assumptions!$C$23/12 -> 54.166667 | J15: =(H15+I15)*Assumptions!$C$25 -> 5.9965 | K15: =H15+I15+J15 -> 405.76317 | L15: =K15*Assumptions!$C$15 -> 101.44079 | M15: =E15*Assumptions!$C$11*100*Assumptions!$C$16 -> 219.375 | N15: =K15*Assumptions!$C$17 -> 14.201711 | O15: =K15*Assumptions!$C$18 -> 8.1152633 | P15: =L15+M15+N15+O15 -> 343.13277 | Q15: =(K15+P15)*Assumptions!$C$19 -> 119.82335 | R15: =(Assumptions!$C$26+Assumptions!$C$27+Assumptions!$C$28+Assumptions!$C$29)/12 -> 71.666667 | S15: =K15+P15+Q15+R15 -> 940.38595
B16: 12 | C16: Franschhoek Cellars Semillon | D16: White | E16: 0.125 | F16: Mid | G16: 50 | H16: =G16*Assumptions!$C$6 -> 360 | I16: =Assumptions!$C$23/12 -> 54.166667 | J16: =(H16+I16)*Assumptions!$C$25 -> 6.2125 | K16: =H16+I16+J16 -> 420.37917 | L16: =K16*Assumptions!$C$15 -> 105.09479 | M16: =E16*Assumptions!$C$11*100*Assumptions!$C$16 -> 210.9375 | N16: =K16*Assumptions!$C$17 -> 14.713271 | O16: =K16*Assumptions!$C$18 -> 8.4075833 | P16: =L16+M16+N16+O16 -> 339.15315 | Q16: =(K16+P16)*Assumptions!$C$19 -> 121.52517 | R16: =(Assumptions!$C$26+Assumptions!$C$27+Assumptions!$C$28+Assumptions!$C$29)/12 -> 71.666667 | S16: =K16+P16+Q16+R16 -> 952.72415
... B21: 17 | C21: Elgin Valley Pinot Noir | D21: Red | E21: 0.13 | F21: Mid | G21: 75 | H21: =G21*Assumptions!$C$6 -> 540 | I21: =Assumptions!$C$23/12 -> 54.166667 | J21: =(H21+I21)*Assumptions!$C$25 -> 8.9125 | K21: =H21+I21+J21 -> 603.07917 | L21: =K21*Assumptions!$C$15 -> 150.76979 | M21: =E21*Assumptions!$C$11*100*Assumptions!$C$16 -> 219.375 | N21: =K21*Assumptions!$C$17 -> 21.107771 | O21: =K21*Assumptions!$C$18 -> 12.061583 | P21: =L21+M21+N21+O21 -> 403.31415 | Q21: =(K21+P21)*Assumptions!$C$19 -> 161.02293 | R21: =(Assumptions!$C$26+Assumptions!$C$27+Assumptions!$C$28+Assumptions!$C$29)/12 -> 71.666667 | S21: =K21+P21+Q21+R21 -> 1239.0829
B22: 18 | C22: Kanonkop Estate Pinotage | D22: Red | E22: 0.145 | F22: Premium | G22: 180 | H22: =G22*Assumptions!$C$6 -> 1296 | I22: =Assumptions!$C$24/12 -> 233.33333 | J22: =(H22+I22)*Assumptions!$C$25 -> 22.94 | K22: =H22+I22+J22 -> 1552.2733 | L22: =K22*Assumptions!$C$15 -> 388.06833 | M22: =E22*Assumptions!$C$11*100*Assumptions!$C$16 -> 244.6875 | N22: =K22*Assumptions!$C$17 -> 54.329567 | O22: =K22*Assumptions!$C$18 -> 31.045467 | P22: =L22+M22+N22+O22 -> 718.13087 | Q22: =(K22+P22)*Assumptions!$C$19 -> 363.26467 | R22: =(Assumptions!$C$26+Assumptions!$C$27+Assumptions!$C$28+Assumptions!$C$29)/12 -> 71.666667 | S22: =K22+P22+Q22+R22 -> 2705.3355
B23: 19 | C23: Meerlust Rubicon | D23: Red | E23: 0.14 | F23: Premium | G23: 250 | H23: =G23*Assumptions!$C$6 -> 1800 | I23: =Assumptions!$C$24/12 -> 233.33333 | J23: =(H23+I23)*Assumptions!$C$25 -> 30.5 | K23: =H23+I23+J23 -> 2063.8333 | L23: =K23*Assumptions!$C$15 -> 515.95833 | M23: =E23*Assumptions!$C$11*100*Assumptions!$C$16 -> 236.25 | N23: =K23*Assumptions!$C$17 -> 72.234167 | O23: =K23*Assumptions!$C$18 -> 41.276667 | P23: =L23+M23+N23+O23 -> 865.71917 | Q23: =(K23+P23)*Assumptions!$C$19 -> 468.7284 | R23: =(Assumptions!$C$26+Assumptions!$C$27+Assumptions!$C$28+Assumptions!$C$29)/12 -> 71.666667 | S23: =K23+P23+Q23+R23 -> 3469.9476
B24: 20 | C24: Hamilton Russell Pinot Noir | D24: Red | E24: 0.13 | F24: Premium | G24: 220 | H24: =G24*Assumptions!$C$6 -> 1584 | I24: =Assumptions!$C$24/12 -> 233.33333 | J24: =(H24+I24)*Assumptions!$C$25 -> 27.26 | K24: =H24+I24+J24 -> 1844.5933 | L24: =K24*Assumptions!$C$15 -> 461.14833 | M24: =E24*Assumptions!$C$11*100*Assumptions!$C$16 -> 219.375 | N24: =K24*Assumptions!$C$17 -> 64.560767 | O24: =K24*Assumptions!$C$18 -> 36.891867 | P24: =L24+M24+N24+O24 -> 781.97597 | Q24: =(K24+P24)*Assumptions!$C$19 -> 420.25109 | R24: =(Assumptions!$C$26+Assumptions!$C$27+Assumptions!$C$28+Assumptions!$C$29)/12 -> 71.666667 | S24: =K24+P24+Q24+R24 -> 3118.4871
B25: 21 | C25: Klein Constantia Vin de Constance | D25: White | E25: 0.14 | F25: Premium | G25: 350 | H25: =G25*Assumptions!$C$6 -> 2520 | I25: =Assumptions!$C$24/12 -> 233.33333 | J25: =(H25+I25)*Assumptions!$C$25 -> 41.3 | K25: =H25+I25+J25 -> 2794.6333 | L25: =K25*Assumptions!$C$15 -> 698.65833 | M25: =E25*Assumptions!$C$11*100*Assumptions!$C$16 -> 236.25 | N25: =K25*Assumptions!$C$17 -> 97.812167 | O25: =K25*Assumptions!$C$18 -> 55.892667 | P25: =L25+M25+N25+O25 -> 1088.6132 | Q25: =(K25+P25)*Assumptions!$C$19 -> 621.31944 | R25: =(Assumptions!$C$26+Assumptions!$C$27+Assumptions!$C$28+Assumptions!$C$29)/12 -> 71.666667 | S25: =K25+P25+Q25+R25 -> 4576.2326
B26: 22 | C26: Boekenhoutskloof Syrah | D26: Red | E26: 0.145 | F26: Premium | G26: 200 | H26: =G26*Assumptions!$C$6 -> 1440 | I26: =Assumptions!$C$24/12 -> 233.33333 | J26: =(H26+I26)*Assumptions!$C$25 -> 25.1 | K26: =H26+I26+J26 -> 1698.4333 | L26: =K26*Assumptions!$C$15 -> 424.60833 | M26: =E26*Assumptions!$C$11*100*Assumptions!$C$16 -> 244.6875 | N26: =K26*Assumptions!$C$17 -> 59.445167 | O26: =K26*Assumptions!$C$18 -> 33.968667 | P26: =L26+M26+N26+O26 -> 762.70967 | Q26: =(K26+P26)*Assumptions!$C$19 -> 393.78288 | R26: =(Assumptions!$C$26+Assumptions!$C$27+Assumptions!$C$28+Assumptions!$C$29)/12 -> 71.666667 | S26: =K26+P26+Q26+R26 -> 2926.5925
B27: 23 | C27: Graham Beck Brut Rose MCC | D27: Sparkling | E27: 0.12 | F27: Premium | G27: 130 | H27: =G27*Assumptions!$C$6 -> 936 | I27: =Assumptions!$C$24/12 -> 233.33333 | J27: =(H27+I27)*Assumptions!$C$25 -> 17.54 | K27: =H27+I27+J27 -> 1186.8733 | L27: =K27*Assumptions!$C$15 -> 296.71833 | M27: =E27*Assumptions!$C$11*100*Assumptions!$C$16 -> 202.5 | N27: =K27*Assumptions!$C$17 -> 41.540567 | O27: =K27*Assumptions!$C$18 -> 23.737467 | P27: =L27+M27+N27+O27 -> 564.49637 | Q27: =(K27+P27)*Assumptions!$C$19 -> 280.21915 | R27: =(Assumptions!$C$26+Assumptions!$C$27+Assumptions!$C$28+Assumptions!$C$29)/12 -> 71.666667 | S27: =K27+P27+Q27+R27 -> 2103.2555
B28: 24 | C28: Simonsig Kaapse Vonkel | D28: Sparkling | E28: 0.115 | F28: Premium | G28: 110 | H28: =G28*Assumptions!$C$6 -> 792 | I28: =Assumptions!$C$24/12 -> 233.33333 | J28: =(H28+I28)*Assumptions!$C$25 -> 15.38 | K28: =H28+I28+J28 -> 1040.7133 | L28: =K28*Assumptions!$C$15 -> 260.17833 | M28: =E28*Assumptions!$C$11*100*Assumptions!$C$16 -> 194.0625 | N28: =K28*Assumptions!$C$17 -> 36.424967 | O28: =K28*Assumptions!$C$18 -> 20.814267 | P28: =L28+M28+N28+O28 -> 511.48007 | Q28: =(K28+P28)*Assumptions!$C$19 -> 248.35094 | R28: =(Assumptions!$C$26+Assumptions!$C$27+Assumptions!$C$28+Assumptions!$C$29)/12 -> 71.666667 | S28: =K28+P28+Q28+R28 -> 1872.211
B29: 25 | C29: Villiera Tradition Brut MCC | D29: Sparkling | E29: 0.12 | F29: Premium | G29: 95 | H29: =G29*Assumptions!$C$6 -> 684 | I29: =Assumptions!$C$23/12 -> 54.166667 | J29: =(H29+I29)*Assumptions!$C$25 -> 11.0725 | K29: =H29+I29+J29 -> 749.23917 | L29: =K29*Assumptions!$C$15 -> 187.30979 | M29: =E29*Assumptions!$C$11*100*Assumptions!$C$16 -> 202.5 | N29: =K29*Assumptions!$C$17 -> 26.223371 | O29: =K29*Assumptions!$C$18 -> 14.984783 | P29: =L29+M29+N29+O29 -> 431.01795 | Q29: =(K29+P29)*Assumptions!$C$19 -> 188.84114 | R29: =(Assumptions!$C$26+Assumptions!$C$27+Assumptions!$C$28+Assumptions!$C$29)/12 -> 71.666667 | S29: =K29+P29+Q29+R29 -> 1440.7649
B30: 26 | C30: Haute Cabriere Chardonnay Pinot Noir | D30: Sparkling | E30: 0.12 | F30: Premium | G30: 140 | H30: =G30*Assumptions!$C$6 -> 1008 | I30: =Assumptions!$C$24/12 -> 233.33333 | J30: =(H30+I30)*Assumptions!$C$25 -> 18.62 | K30: =H30+I30+J30 -> 1259.9533 | L30: =K30*Assumptions!$C$15 -> 314.98833 | M30: =E30*Assumptions!$C$11*100*Assumptions!$C$16 -> 202.5 | N30: =K30*Assumptions!$C$17 -> 44.098367 | O30: =K30*Assumptions!$C$18 -> 25.199067 | P30: =L30+M30+N30+O30 -> 586.78577 | Q30: =(K30+P30)*Assumptions!$C$19 -> 295.47826 | R30: =(Assumptions!$C$26+Assumptions!$C$27+Assumptions!$C$28+Assumptions!$C$29)/12 -> 71.666667 | S30: =K30+P30+Q30+R30 -> 2213.884

Sheet Operating Expenses
B2: MONTHLY OPERATING EXPENSES
B4: Expense Item | C4: Monthly (KES) | D4: Per Bottle (KES) | E4: Notes
B5: WAREHOUSE & STORAGE
B6: Warehouse Rent | C6: 450000 | D6: =C6/Assumptions!$C$10 -> 6.8181818 | E6: Temperature-controlled wine storage
B7: Warehouse Staff (6) | C7: 360000 | D7: =C7/Assumptions!$C$10 -> 5.4545455 | E7: Avg KES 60,000/month each
B8: Utilities (power, water) | C8: 120000 | D8: =C8/Assumptions!$C$10 -> 1.8181818 | E8: Climate control is critical for wine
B9: Warehouse Insurance | C9: 80000 | D9: =C9/Assumptions!$C$10 -> 1.2121212
B10: Stock Shrinkage / Breakage | C10: 200000 | D10: =C10/Assumptions!$C$10 -> 3.030303 | E10: 1% of average inventory value
B11: Subtotal: Warehouse | C11: =SUM(C6:C10) -> 1210000 | D11: =C11/Assumptions!$C$10 -> 18.333333
B13: SALES & DISTRIBUTION
B14: Sales Team (8 reps + 2 managers) | C14: 1200000 | D14: =C14/Assumptions!$C$10 -> 18.181818 | E14: Salaries + commissions
B15: Vehicle Fleet (5 delivery vans) | C15: 400000 | D15: =C15/Assumptions!$C$10 -> 6.0606061 | E15: Fuel, maintenance, insurance
B16: Vehicle Depreciation | C16: 250000 | D16: =C16/Assumptions!$C$10 -> 3.7878788 | E16: Straight-line on delivery fleet
B17: Cold Chain / Refrigerated Transport | C17: 150000 | D17: =C17/Assumptions!$C$10 -> 2.2727273 | E17: Temperature-controlled delivery
B18: Subtotal: Sales & Distribution | C18: =SUM(C14:C17) -> 2000000 | D18: =C18/Assumptions!$C$10 -> 30.30303
B20: ADMINISTRATION
B21: Management (MD, Finance, Operations) | C21: 600000 | D21: =C21/Assumptions!$C$10 -> 9.0909091 | E21: 3 senior staff
B22: Office Rent | C22: 180000 | D22: =C22/Assumptions!$C$10 -> 2.7272727
B23: Office Staff (4) | C23: 280000 | D23: =C23/Assumptions!$C$10 -> 4.2424242 | E23: Admin, accounts, compliance
B24: IT Systems / ERP | C24: 80000 | D24: =C24/Assumptions!$C$10 -> 1.2121212 | E24: Inventory management, eTIMS
B25: Legal & Compliance | C25: 60000 | D25: =C25/Assumptions!$C$10 -> 0.90909091 | E25: Liquor licenses, KEBS, KRA
B26: Audit & Accounting | C26: 50000 | D26: =C26/Assumptions!$C$10 -> 0.75757576
B27: Subtotal: Administration | C27: =SUM(C21:C26) -> 1250000 | D27: =C27/Assumptions!$C$10 -> 18.939394
B29: MARKETING & TRADE
B30: Trade Promotions | C30: 350000 | D30: =C30/Assumptions!$C$10 -> 5.3030303 | E30: Retailer incentives, tastings
B31: Brand Marketing | C31: 200000 | D31: =C31/Assumptions!$C$10 -> 3.030303 | E31: Events, POS materials
B32: Wine Sampling / Tasting Events | C32: 150000 | D32: =C32/Assumptions!$C$10 -> 2.2727273 | E32: Lodge and hotel tastings
B33: Subtotal: Marketing | C33: =SUM(C30:C32) -> 700000 | D33: =C33/Assumptions!$C$10 -> 10.606061
B35: TOTAL OPERATING EXPENSES | C35: =C11+C18+C27+C33 -> 5160000 | D35: =C35/Assumptions!$C$10 -> 78.181818

Sheet Pricing Model
C2: PRICING MODEL - BY SKU AND CHANNEL
C3: OpEx per Bottle (from Operating Expenses): | G3: ='Operating Expenses'!D35 -> 78.181818
B5: # | C5: Wine Name | D5: Segment | E5: Landed Cost (KES) | F5: OpEx Alloc. (KES) | G5: Margin % | H5: Supermarket Price (KES) | I5: Lodge/Hotel Price (KES) | J5: Suggested Retail (KES) | K5: Gross Profit (KES) | L5: GP % | M5: Case Price - Supermarket (KES) | N5: Case Price - Lodge (KES)
B6: 1 | C6: Cape Valley Dry Red | D6: Budget | E6: ='Product Catalog & Landed Cost'!S5 -> 719.12894 | F6: =$G$3 -> 78.181818 | G6: 0.25 | H6: =(E6+F6)/(1-G6) -> 1063.081 | I6: =H6*1.15 -> 1222.5432 | J6: =H6*1.3 -> 1382.0053 | K6: =H6-E6-F6 -> 265.77025 | L6: =K6/H6 -> 0.25 | M6: =H6*12 -> 12756.972 | N6: =I6*12 -> 14670.518
B7: 2 | C7: Cape Valley Sauvignon Blanc | D7: Budget | E7: ='Product Catalog & Landed Cost'!S6 -> 687.21574 | F7: =$G$3 -> 78.181818 | G7: 0.25 | H7: =(E7+F7)/(1-G7) -> 1020.5301 | I7: =H7*1.15 -> 1173.6096 | J7: =H7*1.3 -> 1326.6891 | K7: =H7-E7-F7 -> 255.13252 | L7: =K7/H7 -> 0.25 | M7: =H7*12 -> 12246.361 | N7: =I7*12 -> 14083.315
B8: 3 | C8: Cape Valley Rose | D8: Budget | E8: ='Product Catalog & Landed Cost'!S7 -> 688.49109 | F8: =$G$3 -> 78.181818 | G8: 0.25 | H8: =(E8+F8)/(1-G8) -> 1022.2305 | I8: =H8*1.15 -> 1175.5651 | J8: =H8*1.3 -> 1328.8997 | K8: =H8-E8-F8 -> 255.55764 | L8: =K8/H8 -> 0.25 | M8: =H8*12 -> 12266.767 | N8: =I8*12 -> 14106.782
B9: 4 | C9: Vineyard Select Shiraz | D9: Budget | E9: ='Product Catalog & Landed Cost'!S8 -> 806.35639 | F9: =$G$3 -> 78.181818 | G9: 0.25 | H9: =(E9+F9)/(1-G9) -> 1179.3843 | I9: =H9*1.15 -> 1356.2919 | J9: =H9*1.3 -> 1533.1996 | K9: =H9-E9-F9 -> 294.84607 | L9: =K9/H9 -> 0.25 | M9: =H9*12 -> 14152.611 | N9: =I9*12 -> 16275.503
B10: 5 | C10: Vineyard Select Chenin Blanc | D10: Budget | E10: ='Product Catalog & Landed Cost'!S9 -> 774.44319 | F10: =$G$3 -> 78.181818 | G10: 0.25 | H10: =(E10+F10)/(1-G10) -> 1136.8333 | I10: =H10*1.15 -> 1307.3583 | J10: =H10*1.3 -> 1477.8834 | K10: =H10-E10-F10 -> 284.20834 | L10: =K10/H10 -> 0.25 | M10: =H10*12 -> 13642 | N10: =I10*12 -> 15688.3
B11: 6 | C11: Vineyard Select Dry Rose | D11: Budget | E11: ='Product Catalog & Landed Cost'!S10 -> 753.59284 | F11: =$G$3 -> 78.181818 | G11: 0.25 | H11: =(E11+F11)/(1-G11) -> 1109.0329 | I11: =H11*1.15 -> 1275.3878 | J11: =H11*1.3 -> 1441.7427 | K11: =H11-E11-F11 -> 277.25822 | L11: =K11/H11 -> 0.25 | M11: =H11*12 -> 13308.395 | N11: =I11*12 -> 15304.654
B12: 7 | C12: Harvest Moon Pinotage | D12: Budget | E12: ='Product Catalog & Landed Cost'!S11 -> 849.33244 | F12: =$G$3 -> 78.181818 | G12: 0.25 | H12: =(E12+F12)/(1-G12) -> 1236.6857 | I12: =H12*1.15 -> 1422.1885 | J12: =H12*1.3 -> 1607.6914 | K12: =H12-E12-F12 -> 309.17142 | L12: =K12/H12 -> 0.25 | M12: =H12*12 -> 14840.228 | N12: =I12*12 -> 17066.262
B13: 8 | C13: Harvest Moon Chardonnay | D13: Budget | E13: ='Product Catalog & Landed Cost'!S12 -> 807.63174 | F13: =$G$3 -> 78.181818 | G13: 0.25 | H13: =(E13+F13)/(1-G13) -> 1181.0847 | I13: =H13*1.15 -> 1358.2475 | J13: =H13*1.3 -> 1535.4102 | K13: =H13-E13-F13 -> 295.27119 | L13: =K13/H13 -> 0.25 | M13: =H13*12 -> 14173.017 | N13: =I13*12 -> 16298.97
B14: 9 | C14: Stellenbosch Hills Cabernet Sauvignon | D14: Mid | E14: ='Product Catalog & Landed Cost'!S13 -> 1037.4009 | F14: =$G$3 -> 78.181818 | G14: 0.3 | H14: =(E14+F14)/(1-G14) -> 1593.6896 | I14: =H14*1.15 -> 1832.743 | J14: =H14*1.3 -> 2071.7965 | K14: =H14-E14-F14 -> 478.10688 | L14: =K14/H14 -> 0.3 | M14: =H14*12 -> 19124.275 | N14: =I14*12 -> 21992.916
B15: 10 | C15: Stellenbosch Hills Merlot | D15: Mid | E15: ='Product Catalog & Landed Cost'!S14 -> 994.42485 | F15: =$G$3 -> 78.181818 | G15: 0.3 | H15: =(E15+F15)/(1-G15) -> 1532.2952 | I15: =H15*1.15 -> 1762.1395 | J15: =H15*1.3 -> 1991.9838 | K15: =H15-E15-F15 -> 459.68857 | L15: =K15/H15 -> 0.3 | M15: =H15*12 -> 18387.543 | N15: =I15*12 -> 21145.674
B16: 11 | C16: Robertson Valley Sauvignon Blanc | D16: Mid | E16: ='Product Catalog & Landed Cost'!S15 -> 940.38595 | F16: =$G$3 -> 78.181818 | G16: 0.3 | H16: =(E16+F16)/(1-G16) -> 1455.0968 | I16: =H16*1.15 -> 1673.3613 | J16: =H16*1.3 -> 1891.6259 | K16: =H16-E16-F16 -> 436.52904 | L16: =K16/H16 -> 0.3 | M16: =H16*12 -> 17461.162 | N16: =I16*12 -> 20080.336
B17: 12 | C17: Franschhoek Cellars Semillon | D17: Mid | E17: ='Product Catalog & Landed Cost'!S16 -> 952.72415 | F17: =$G$3 -> 78.181818 | G17: 0.3 | H17: =(E17+F17)/(1-G17) -> 1472.7228 | I17: =H17*1.15 -> 1693.6312 | J17: =H17*1.3 -> 1914.5397 | K17: =H17-E17-F17 -> 441.81684 | L17: =K17/H17 -> 0.3 | M17: =H17*12 -> 17672.674 | N17: =I17*12 -> 20323.575
... B31: 26 | C31: Haute Cabriere Chardonnay Pinot Noir | D31: Premium | E31: ='Product Catalog & Landed Cost'!S30 -> 2213.884 | F31: =$G$3 -> 78.181818 | G31: 0.35 | H31: =(E31+F31)/(1-G31) -> 3526.2551 | I31: =H31*1.15 -> 4055.1934 | J31: =H31*1.3 -> 4584.1317 | K31: =H31-E31-F31 -> 1234.1893 | L31: =K31/H31 -> 0.35 | M31: =H31*12 -> 42315.062 | N31: =I31*12 -> 48662.321

Sheet Monthly P&L
B2: PROJECTED MONTHLY PROFIT & LOSS
B4: Line Item | C4: Monthly (KES) | D4: % of Revenue
B5: Cases Sold | C5: =Assumptions!C8 -> 5500
B6: Bottles Sold | C6: =Assumptions!C10 -> 66000
B8: Revenue (Avg Supermarket Price x Bottles) | C8: =AVERAGE('Pricing Model'!H6:H31)*C6 -> 1.580597e+08 | D8: 1
B10: COST OF GOODS SOLD
B11: Avg Landed Cost per Bottle x Bottles Sold | C11: =AVERAGE('Product Catalog & Landed Cost'!S5:S30)*C6 -> 1.017105e+08 | D11: =C11/C8 -> 0.64349419
B12: TOTAL COGS | C12: =C11 -> 1.017105e+08 | D12: =C12/C8 -> 0.64349419
B14: GROSS PROFIT | C14: =C8-C12 -> 56349203 | D14: =C14/C8 -> 0.35650581
B16: OPERATING EXPENSES
B17: Subtotal: Warehouse | C17: ='Operating Expenses'!C11 -> 1210000 | D17: =C17/C8 -> 0.0076553351
B18: Subtotal: Sales & Distribution | C18: ='Operating Expenses'!C18 -> 2000000 | D18: =C18/C8 -> 0.012653447
B19: Subtotal: Administration | C19: ='Operating Expenses'!C27 -> 1250000 | D19: =C19/C8 -> 0.0079084041
B20: Subtotal: Marketing | C20: ='Operating Expenses'!C33 -> 700000 | D20: =C20/C8 -> 0.0044287063
B21: TOTAL OPERATING EXPENSES | C21: ='Operating Expenses'!C35 -> 5160000 | D21: =C21/C8 -> 0.032645892
B23: OPERATING PROFIT (EBIT) | C23: =C14-C21 -> 51189203 | D23: =C23/C8 -> 0.32385992
B25: Corporate Tax (30%) | C25: =IF(C23>0,C23*Assumptions!$C$52,0) -> 15356761
B26: NET PROFIT AFTER TAX | C26: =C23-C25 -> 35832442 | D26: =C26/C8 -> 0.22670194

Sheet Sensitivity Analysis
B2: SENSITIVITY: EXCHANGE RATE IMPACT ON LANDED COST
B4: Base ZAR/KES Rate: | C4: =Assumptions!C6 -> 7.2
B5: Avg Landed Cost at Base Rate: | C5: =AVERAGE('Product Catalog & Landed Cost'!S5:S30) -> 1541.0682
B7: ZAR/KES Rate | C7: 6.5 | D7: 7 | E7: 7.2 | F7: 7.5 | G7: 8
B8: Avg FOB in KES (Budget wine, ZAR 30) | C8: =30*C$7 -> 195 | D8: =30*D$7 -> 210 | E8: =30*E$7 -> 216 | F8: =30*F$7 -> 225 | G8: =30*G$7 -> 240
B9: Avg FOB in KES (Mid wine, ZAR 60) | C9: =60*C$7 -> 390 | D9: =60*D$7 -> 420 | E9: =60*E$7 -> 432 | F9: =60*F$7 -> 450 | G9: =60*G$7 -> 480
B10: Avg FOB in KES (Premium wine, ZAR 180) | C10: =180*C$7 -> 1170 | D10: =180*D$7 -> 1260 | E10: =180*E$7 -> 1296 | F10: =180*F$7 -> 1350 | G10: =180*G$7 -> 1440
B13: SENSITIVITY: VOLUME IMPACT ON OPEX PER BOTTLE
B15: Monthly Cases | C15: 3000 | D15: 4000 | E15: 5500 | F15: 7000 | G15: 10000
B16: Monthly Bottles | C16: =C$15*12 -> 36000 | D16: =D$15*12 -> 48000 | E16: =E$15*12 -> 66000 | F16: =F$15*12 -> 84000 | G16: =G$15*12 -> 120000
B17: Total OpEx (KES) | C17: ='Operating Expenses'!C35 -> 5160000 | D17: ='Operating Expenses'!C35 -> 5160000 | E17: ='Operating Expenses'!C35 -> 5160000 | F17: ='Operating Expenses'!C35 -> 5160000 | G17: ='Operating Expenses'!C35 -> 5160000
B18: OpEx per Bottle (KES) | C18: =C17/C16 -> 143.33333 | D18: =D17/D16 -> 107.5 | E18: =E17/E16 -> 78.181818 | F18: =F17/F16 -> 61.428571 | G18: =G17/G16 -> 43
